odoo/addons/rental_base/README.rst
odoo/addons/rental_base/__init__.py
odoo/addons/rental_base/__manifest__.py
odoo/addons/rental_base/README/CONTRIBUTORS.rst
odoo/addons/rental_base/README/DESCRIPTION.rst
odoo/addons/rental_base/README/HISTORY.rst
odoo/addons/rental_base/README/USAGE.rst
odoo/addons/rental_base/data/ir_sequence_data.xml
odoo/addons/rental_base/data/order_type_data.xml
odoo/addons/rental_base/data/product_uom_data.xml
odoo/addons/rental_base/i18n/de.po
odoo/addons/rental_base/i18n/fr.po
odoo/addons/rental_base/i18n/rental_base.pot
odoo/addons/rental_base/models/__init__.py
odoo/addons/rental_base/models/ir_sequence.py
odoo/addons/rental_base/models/product.py
odoo/addons/rental_base/models/sale.py
odoo/addons/rental_base/security/ir.model.access.csv
odoo/addons/rental_base/static/description/icon.png
odoo/addons/rental_base/static/description/index.html
odoo/addons/rental_base/tests/__init__.py
odoo/addons/rental_base/tests/stock_common.py
odoo/addons/rental_base/tests/test_update_time_rental_order.py
odoo/addons/rental_base/views/menu_view.xml
odoo/addons/rental_base/views/product_views.xml
odoo/addons/rental_base/views/res_config_settings_view.xml
odoo/addons/rental_base/views/sale_view.xml
odoo/addons/rental_base/views/stock_picking_views.xml
odoo/addons/rental_base/wizard/__init__.py
odoo/addons/rental_base/wizard/update_sale_line_date.py
odoo/addons/rental_base/wizard/update_sale_line_date_view.xml
odoo14_addon_rental_base-14.0.1.0.1.dist-info/METADATA
odoo14_addon_rental_base-14.0.1.0.1.dist-info/WHEEL
odoo14_addon_rental_base-14.0.1.0.1.dist-info/top_level.txt
odoo14_addon_rental_base-14.0.1.0.1.dist-info/RECORD
